README.rst
setup.cfg
setup.py
SajadKalma.egg-info/PKG-INFO
SajadKalma.egg-info/SOURCES.txt
SajadKalma.egg-info/dependency_links.txt
SajadKalma.egg-info/top_level.txt
SajadMadrid/Builtins.py
SajadMadrid/BytecodeCaching.py
SajadMadrid/Bytecodes.py
SajadMadrid/CacheCleanup.py
SajadMadrid/Constants.py
SajadMadrid/Errors.py
SajadMadrid/HardImportRegistry.py
SajadMadrid/MainControl.py
SajadMadrid/ModuleRegistry.py
SajadMadrid/OptionParsing.py
SajadMadrid/Options.py
SajadMadrid/OutputDirectories.py
SajadMadrid/PostProcessing.py
SajadMadrid/Progress.py
SajadMadrid/PythonFlavors.py
SajadMadrid/PythonOperators.py
SajadMadrid/PythonVersions.py
SajadMadrid/Serialization.py
SajadMadrid/SourceCodeReferences.py
SajadMadrid/Tracing.py
SajadMadrid/TreeXML.py
SajadMadrid/Variables.py
SajadMadrid/Version.py
SajadMadrid/__init__.py
SajadMadrid/__main__.py
SajadMadrid/__past__.py
SajadMadrid/build/Backend.scons
SajadMadrid/build/CCompilerVersion.scons
SajadMadrid/build/DataComposerInterface.py
SajadMadrid/build/Offsets.scons
SajadMadrid/build/Onefile.scons
SajadMadrid/build/SconsCaching.py
SajadMadrid/build/SconsCompilerSettings.py
SajadMadrid/build/SconsHacks.py
SajadMadrid/build/SconsInterface.py
SajadMadrid/build/SconsProgress.py
SajadMadrid/build/SconsSpawn.py
SajadMadrid/build/SconsUtils.py
SajadMadrid/build/__init__.py
SajadMadrid/build/include/SajadMadrid/allocator.h
SajadMadrid/build/include/SajadMadrid/builtins.h
SajadMadrid/build/include/SajadMadrid/calling.h
SajadMadrid/build/include/SajadMadrid/checkers.h
SajadMadrid/build/include/SajadMadrid/checksum_tools.h
SajadMadrid/build/include/SajadMadrid/compiled_asyncgen.h
SajadMadrid/build/include/SajadMadrid/compiled_cell.h
SajadMadrid/build/include/SajadMadrid/compiled_coroutine.h
SajadMadrid/build/include/SajadMadrid/compiled_frame.h
SajadMadrid/build/include/SajadMadrid/compiled_function.h
SajadMadrid/build/include/SajadMadrid/compiled_generator.h
SajadMadrid/build/include/SajadMadrid/compiled_method.h
SajadMadrid/build/include/SajadMadrid/constants.h
SajadMadrid/build/include/SajadMadrid/constants_blob.h
SajadMadrid/build/include/SajadMadrid/debug_settings.h
